{
  "لڑکی کو پردے کے بغیر دیکھیں تو کیا کریں گے؟": [
    "میں نظر جھکا لوں گا",
    "اس کو ڈانٹ دونگا",
    "پردے کیلۓ مجبور کرونگا",
    "کچھ نہیں کروں گا",
    "0"
  ],
  "اگر ایئرفورس کا کوئی آفیسر آپکو داڑھی مونڈوانے کا کہے تو آپ کیا کریں گے؟": [
    "نہیں مونڈواوں گا",
    "۔ PAF کا اس سے کوئ تعلق نہیں۔",
    "مونڈوائيں گے",
    "کچھ کہہ نہیں سکتے",
    "2"
  ],
  "کیا عورت امامت کر سکتی ہے؟": [
    "متفق",
    "نا متفق",
    "بلکل متفق",
    "کچھ کہہ نہیں سکتے",
    "1"
  ],
  "اگر کوئی لڑکی گھر سے کسی لڑکے کے ساتھ بھاگ جائے تو لڑکی کو قتل کر دینا چاہیے۔": [
    "متفق",
    "بلکل متفق",
    "نا متفق",
    "دونوں کو قتل کر دیں",
    "2"
  ],
  "اگر آپکا فرقہ آپ کو دوسرے فرقے کے خلاف کوئی کام کرنے کو کہے تو۔": [
    "نہیں کروں گا",
    "کروں گا",
    "اپنے فرقے سے پوچھوں گا",
    "میں قران و سنت کی روشنی میں فیصلہ کروں گا",
    "3"
  ],
  "قران مجید کی ۳۰ نمبر سورہ مبارکہ کونسی ہے؟": [
    "سورۃ روم",
    "سورۃ المریم",
    "سورۃ النمل",
    "سورۃ سجدہ",
    "0"
  ],
  "اگر آپ کے فرقے کی لڑکی کسی غیر مذہب کو اختیار کرے تو آپ کیا کریں گے؟": [
    "قتل کردوں گا",
    "اسکو بتاؤں گا کہ نیا فرقہ برا ہے",
    "میں اسکے اصلاح کرنے کی کوشش کروں گا",
    "کچھ نہیں کروں گا",
    "2"
  ],
  "اگر آپ کا بھائی غیر مسلم ہو جائے تو۔": [
    "اس سے کبھی بات نہیں کروں گا",
    "اس سے علیحدگی اختیار کروں گا",
    "قتل کردوں گا",
    "کچھ نہیں کروں گا",
    "1"
  ],
  "اگر کوئی آپ کا فرقہ چھوڑ کر دوسرے فرقے کو اپنائے تو آپ کیا کریں گے؟": [
    "کچھ نہیں کروں گا",
    "لڑائی جھگڑا کروں گا",
    "دین میں کوئی جبر نہیں",
    "میں بھی اس فرقے میں چلا جاگا",
    "2"
  ],
  "سیریز مکمل کریں۔۔۔۔۔۔۔۔۔۔2,5,8,11": [
    "13",
    "17",
    "21",
    "14",
    "3"
  ],
  "لڑکی کی شادی میں اگر والدین کی رضامندی شامل نہ ہو تو شادی ہوجاتی ہے۔": [
    "نا متفق",
    "کچھ نہیں سکتے",
    "متفق",
    "بالکل متفق",
    "2"
  ],
  "اگر کوئی آپ کے سامنے آپ کے فرقے کی برائی کرے تو آپ کیا کریں گے؟": [
    "میں اس بات کا رخ دوسری طرف موڑ دوں گا",
    "جھگڑا کروں گا",
    "دلائل دوںگا",
    "کچھ نہیں کروںگا",
    "0"
  ],
  "کیا بے روزگار نوجوان مختلف تنظیموں میں شمولیت اختیار کر رہے ہیں؟": [
    "متفق",
    "نا متفق",
    "بالکل متفق",
    "کچھ کہہ نہیں سکتے",
    "1"
  ],
  "اگر بسکٹ کے تین پیکٹس کی قیمت 21 روپے ہے تو 5 پیکٹوں کی قیمت کیا ہوگی؟": [
    "Rs 30",
    "Rs 20",
    "Rs 25",
    "Rs 35",
    "3"
  ],
  "ملک کو مضبوط بنانے اور مستحکم کرنے میں کس کا اہم کردار ہے۔": [
    "کا PAF",
    "سب کی مسلسل کوششوں کا",
    "ملٹری ڈکٹیٹرز کا",
    "پولیٹیشنز کا",
    "1"
  ],
  "ملک میں تبدیلی نظر نہ آنے کی وجہ ہے۔": [
    "الیکشن",
    "ملٹری ڈکٹیٹرز",
    "سول بیئروکریسی",
    "پرانے نظام کی بھرپور حمایت",
    "3"
  ],
  "اگر دو فرقوں میں شادی ہوجائے تو نکاح ہوگا؟": [
    "نہیں ہوگا",
    "کچھ کہہ نہیں سکتے",
    "امام صاحب سے پوچھوں گا",
    "نکاح ہوجائے گا کیونکہ دونوں کا تعلق اسلام سے ہے۔",
    "3"
  ],
  "کیا اسلام کسی کو اختلاف رائے کا حق نہیں دیتا؟": [
    "نا متفق",
    "متفق",
    "بالکل متفق",
    "کچھ کہہ نہیں سکتے",
    "0"
  ],
  "مختلف کیا ہے طوطہ، کوا، چیل، بطخ، چڑیا۔": [
    "کوا",
    "طوطہ",
    "چڑیا",
    "بطخ",
    "3"
  ],
  "کیا آپ کا شمار فرقے کے اہم لوگوں میں ہونا چاہیے؟": [
    "متفق",
    "بالکل متفق",
    "کچھ کہہ نہیں سکتے",
    "نا متفق",
    "3"
  ],
  "کیا آپ کا فرقہ سب فرقوں سے زیادہ اچھا ہے؟": [
    "نا متفق",
    "متفق",
    "بالکل متفق",
    "کچھ کہہ نہیں سکتے",
    "0"
  ],
  "اگر آپ سنی یا بریلوی ہیں تو آپ شیعہ امام کے پیچھے نماز ادا کریں گے۔": [
    "نا متفق",
    "کچھ کہہ نہیں سکتے",
    "امام صاحب سے پوچھوں گا",
    "متفق",
    "3"
  ],
  "اسامہ بن لادن کا تعلق کس گروہ سے تھا؟": [
    "نادرن الائینس",
    "آئی ایس آئی",
    "راء",
    "القاعدہ",
    "3"
  ],
  "کیا کچھ مدارس فساد پھیلانے کی اصل وجہ ہیں؟": [
    "متفق",
    "بالکل متفق",
    "کچھ کہہ نہیں سکتے",
    "متفق",
    "0"
  ],
  "کیا آپ دوسرے فرقے کی مسجد میں نماز ادا کریں گے؟": [
    "نا متفق",
    "کچھ کہہ نہیں سکتے",
    "متفق",
    "امام صاحب سے پوچھوں گا",
    "2"
  ],
  "ھدھد کا ذکر قرآن مجید کی کس سورۃمبارکہ میں ہے؟": [
    "سورۃ العصر",
    "سورۃ الاعمران",
    "سورۃ المریم",
    "سورۃ النمل",
    "3"
  ],
  "قران مجید میں پانچواں سجدہ کس سورہ میں ہے؟": [
    "سورۃ النمل",
    "سورۃ العصر",
    "سورۃ سجدہ",
    "سورۃ المریم",
    "3"
  ],
  "کس غزوہ میں حضور ﷺ کی چار نمازیں قضا ہویں؟": [
    "غزوہ احد",
    "غزوہ خندق",
    "غزوہ بدر",
    "غزوہ تبوک",
    "1"
  ],
  "قرآن مجید کی کس سورۃ مبارکہ کے درمیان بسم اللّٰہ آتی ہے؟": [
    "سورۃ سجدہ",
    "سورۃ الرحمان",
    "سورۃ المریم",
    "سورۃ النمل",
    "3"
  ],
  "کس غزوہ میں حضور ﷺ کے دو دانت مبارک شہید ہوئے؟": [
    "غزوہ تبوک",
    "غزوہ خندق",
    "غزوہ احد",
    "غزوہ بدر",
    "2"
  ],
  "کیا لڑکیوں کو لڑکوں کی نسبت کم تعلیم دینی چاہیے؟": [
    "متفق",
    "کچھ کہہ نہیں سکتے",
    "بالکل متفق",
    "نا متفق",
    "3"
  ],
  "کیا دنیاوی تعلیم معاشرے کی خرابی کی اصل وجہ ہے؟": [
    "متفق",
    "بالکل متفق",
    "نا متفق",
    "کچھ کہہ نہیں سکتے",
    "2"
  ],
  "قتل کس صورت میں جائز ہے؟": [
    "بدلہ کی صورت میں",
    "غیرت کی صورت میں",
    "دوسرے فرقے کی صورت میں",
    "کسی صورت میں جائز نہیں",
    "3"
  ],
  "فرقے کی محبت میں آپ کس حد تک جائیں گے۔": [
    "ہر حد تک",
    "دلائل دوںگا",
    "کچھ نہیں کروں گا",
    "میں فرقہ واریت سے بالاتر ہوں",
    "3"
  ],
  "کیا آپ اپنے بیٹے  کو بڑے ہوکر عالم دین بنائیں گے؟": [
    "جی ہاں",
    "جی نہیں",
    "جہاد پر بھیجوں گا",
    "کوئی رائے نہیں",
    "3"
  ],
  "کیا شادیاں دھوم دھام سے کرنی چاہیے؟": [
    "متفق",
    "بالکل متفق",
    "کچھ کہہ نہیں سکتے",
    "نا متفق",
    "3"
  ],
  "کیا عورت کو وراثت میں حصہ دینا چاہیے؟": [
    "متفق",
    "نا متفق",
    "کچھ کہہ نہیں سکتے",
    "بالکل متفق",
    "0"
  ],
  "اگر ایئر فورس میں آپ سے کہا جائے کہ پہاڑی سے چھلانگ لگادیں تو؟": [
    "نا متفق",
    "کا اس سے کوئی کام نہیں PAF",
    "مجبور نہیں کر سکتی PAF",
    "متفق (ضروری نہیں کہ بڑی چھلانگ ہو)۔",
    "3"
  ],
  "اگر آپ کے فرقے کی لڑکی کسی دوسرے فرقے کے لڑکے سے شادی کرے تو کیا کریں گے؟": [
    "قتل کردوں گا",
    "میں فرقہ واریت سے بالاتر ہوں",
    "بات نہیں کروں گا",
    "کچھ نہیں کروں گا",
    "1"
  ],
  "آپکا فرقہ آپکے لیے کیا کر سکتا ہے؟": [
    "کچھ بھی نہیں",
    "مالیاتی فائدہ",
    "دوسروں سے بچا سکتا ہے",
    "کوئی رائے نہیں",
    "0"
  ],
  "کونسی نفلی عبادت ہے جسکی جماعت ہوتی ہے؟": [
    "نماز تہجد",
    "شکرانے کے نوافل",
    "صٰلوۃ تسبیح",
    "اس میں سے کوئی بھی نہیں",
    "3"
  ],
  "آپکے فرقے کے لوگ سب سے اچھے ہیں۔": [
    "متفق",
    "بالکل متفق",
    "کچھ کہہ نہیں سکتے",
    "نا متفق",
    "3"
  ],
  "پردہ کرنے کا مطلب کیا صرف نقاب اوڑھنا ہی ہے؟": [
    "نا متفق",
    "متفق",
    "بالکل متفق",
    "کچھ کہہ نہیں سکتے",
    "0"
  ],
  "کیا $PAF$ کے ورکرز کو $PAF$ سے زیادہ سیاست سے دلچسپی رکھنی چاہیۓ۔": [
    "متفق",
    "بالکل متفق",
    "نا متفق",
    "کچھ کہہ نہیں سکتے",
    "2"
  ],
  "پاکستان میں صرف ایک ہی فرقہ کے لوگوں کو زندگی گزارنے کا حق ہے۔": [
    "نا متفق",
    "متفق",
    "بالکل متفق",
    "کچھ کہہ نہیں سکتے",
    "0"
  ],
  "اگر ایک درجن مالٹوں کی قیمت 84 روپے ہے تو 2.5 درجن مالٹوں کی قیمت بتائیں؟": [
    "Rs 168",
    "Rs 120",
    "Rs 220",
    "Rs 210",
    "3"
  ],
  "کیا مذہب کی بنا پر کسی کو قتل کرنا جائز ہے؟": [
    "متفق",
    "بالکل متفق",
    "نا متفق",
    "کچھ کہہ نہیں سکتے",
    "2"
  ],
  "کیا بحث کرنا درست بات ہے؟": [
    "بالکل متفق",
    "نا متفق",
    "کچھ کہہ نہیں سکتے",
    "متفق",
    "1"
  ],
  "آپ ایک شہر سے دوسرے شہر میں سفر کررہے ہیں اور راستے میں نماز کا وقت آگیا ہے کیا نماز دوسرے مسلک کی مسجد میں ادا کرنی چاہیے؟": [
    "نا متفق",
    "بالکل متفق",
    "امام صاحب سے پوچھوں گا",
    "متفق",
    "3"
  ],
  "آپ کی نظر میں طالبان کون ہیں؟": [
    "دہشت گرد",
    "امن پسند",
    "کچھ کہہ نہیں سکتے",
    "مجاہدین",
    "2"
  ],
  "اگر ایک گاڑی 6 کلومیٹر کا فاصلہ 4 منٹ میں طے کرتی ہے تو 18 کلومیٹر کا فاصلہ کتنی دیر میں طے کرے گی؟": [
    "12min",
    "8min",
    "18min",
    "کوئی بھی نہیں",
    "0"
  ],
  "اگر 10 مارکرز کی قیمت 5 روپے ہے تو 30 مارکرز کی قیمت کتنی ہوگی؟": [
    "10",
    "30",
    "15",
    "کوئی بھی نہیں",
    "2"
  ],
  "اگر ایک مشین 8 گھنٹوں میں 6 گاڑیاں دھوتی ہے تو وہی مشین 4 گھنٹوں میں کتنی گاڑیاں دھوئے گی؟": [
    "5",
    "7",
    "10",
    "3",
    "3"
  ],
  "آپ کے خیال میں جوتے چمڑے سے کیوں بنائے جاتے ہیں؟": [
    "چمڑا پائیدار ہوتا ہے",
    "آسانی سے مل جاتا ہے",
    "خوشبوں اچھی ہوتی ہے",
    "لاگت کم آتی ہے",
    "0"
  ],
  "اگر ایک کوچ میں 22 مسافر سفر کر سکتے ہیں تو 199 مسافر کتنی کوچیز میں سفر کریں گے۔": [
    "9",
    "8",
    "11",
    "10",
    "3"
  ],
  "اگر ایک دوسرے مسلک کا لڑکا آپ کے ساتھ پڑھتا ہے تو آپ کیا کریں گے؟": [
    "کچھ نہیں کروں گا",
    "اس کے ساتھ نہیں بولوں گا",
    "پڑھائی میں مدد کروں گا",
    "بات چیت کروں گا",
    "2"
  ],
  "ٹیلیفون کس نے ایجاد کیا؟": [
    "نیوٹن",
    "مارکونی",
    "آئن سٹائن",
    "گراہم بیل",
    "3"
  ],
  "اگر ایک مزدور 3 گھنٹوں میں 5 گاڑیاں دھوتا ہے تو وہ 9 گھنٹوں میں کتنی گاڑیاں دھوئے گا؟": [
    "22",
    "15",
    "17",
    "10",
    "1"
  ],
  "ترقی کا راز اپنے مسلک پر ڈٹ جانے میں ہے۔": [
    "نا متفق",
    "متفق",
    "کچھ کہہ نہیں سکتے",
    "بلکل متفق",
    "0"
  ],
  "کیا صرف نقطہ چینی ہی مسائل کا حل ہے؟": [
    "متفق",
    "نا متفق",
    "کچھ کہہ نہیں سکتے",
    "بلکل متفق",
    "1"
  ],
  "آجکل کی نوجوان نسل بےروزگاری سے تنگ آکر جہاد کرتی ہے۔": [
    "متفق",
    "نا متفق",
    "کچھ کہہ نہیں سکتے",
    "بلکل متفق",
    "1"
  ],
  "کیا پردہ کرنے سے ہی عورت کی صحیح تربیت ہوتی ہے؟": [
    "متفق",
    "نا متفق",
    "کچھ کہہ نہیں سکتے",
    "بلکل متفق",
    "1"
  ],
  "اگر ایک مکان کا 6 ماہ کا کرایہ 36000 ہے تو ایک ماہ کا کرایہ کتنا ہوگا؟": [
    "Rs 5000",
    "Rs 9000",
    "Rs 7000",
    "Rs 6000",
    "4"
  ],
  "کیا امریکہ میں 9/11 کا واقعہ ٹھیک تھا؟": [
    "متفق",
    "نا متفق",
    "کچھ کہہ نہیں سکتے",
    "بلکل متفق",
    "1"
  ],
  "کیا ہمیں عالمی جہاد کی سربراہی کرنی چاہیے؟": [
    "متفق",
    "نا متفق",
    "کچھ کہہ نہیں سکتے",
    "بلکل متفق",
    "1"
  ],
  "کسی پڑوسی ملک کے علماء کی ہر بات ماننا ضروری سمجھتے ہیں؟": [
    "متفق",
    "نا متفق",
    "کچھ کہہ نہیں سکتے",
    "بلکل متفق",
    "1"
  ],
  "فرقہ واریت معاشرے کے بگاڑ کا سبب ہے۔": [
    "متفق",
    "نا متفق",
    "کچھ کہہ نہیں سکتے",
    "بلکل متفق",
    "2"
  ],
  "کوئی شخص اس وقت تک مسلمان نہیں ہوسکتا جب تک کہ وہ مخالف فرقے کو قتل نہ کردے": [
    "متفق",
    "نا متفق",
    "کچھ کہہ نہیں سکتے",
    "بلکل متفق",
    "1"
  ],
  "بےروزگاری کا سب سے بڑا سبب کیا ہے؟": [
    "تعلیم",
    "دہشت گردی",
    "غربت",
    "ملکی وسائل کا کم ہونا",
    "3"
  ],
  "لڑکیوں کو دینی تعلیم کے علاوہ جدید تعلیم بھی دینی چاہیے؟": [
    "متفق",
    "نا متفق",
    "کچھ کہہ نہیں سکتے",
    "بلکل متفق",
    "3"
  ],
  "اگر 6 پنسلوں کی قیمت 30 روپے ہے تو 22 پنسلوں کی قیمت کیا ہوگی؟": [
    "Rs 110",
    "Rs 44",
    "Rs 75",
    "ان میں سے کوئی بھی نہیں",
    "0"
  ],
  "بیٹی سے زیادہ بیٹے کی خدمت کرنی چاہیے۔": [
    "متفق",
    "نا متفق",
    "کچھ کہہ نہیں سکتے",
    "بلکل متفق",
    "1"
  ],
  "عورت کو صرف گھر کی چار دیواری میں رکھنا چاہیے۔": [
    "متفق",
    "نا متفق",
    "کچھ کہہ نہیں سکتے",
    "بلکل متفق",
    "1"
  ],
  "کیا آپ دوسرے مسلک کے لوگوں کے ساتھ دوستی کریں گے؟": [
    "جی ہاں",
    "جی نہیں",
    "بلکل نہیں",
    "کچھ کہہ نہیں سکتا",
    "1"
  ],
  "A,E,...,O,U: سلسلہ مکمل کریں": [
    "I",
    "Q",
    "M",
    "P",
    "0"
  ],
  "جب بابری مسجد پر جب ہندوؤں نے حملہ کیا تو جواب میں مسلمانوں کو بھی ان کے کے مندروں پر حملہ کرنا چاہیے تھا؟": [
    "متفق",
    "نا متفق",
    "بلکل متفق",
    "ظلم کا جواب ظلم سے نہیں دینا",
    "3"
  ],
  "مذہب انسان کیلئے کیا ہے؟": [
    "کچھ نہیں",
    "ضابطہ حیات",
    "زندگی اور موت",
    "معلوم نہیں",
    "1"
  ],
  "انسان کی دو نفسیاتی خواہشات کیا ہیں؟": [
    "گھر اور پیسہ",
    "علم و ہنر",
    "مال و دولت",
    "امن و سکون",
    "3"
  ],
  "آپ کی بہن کپڑے اتار رہی ہے تو آپ کیا کریں گے؟": [
    "قتل کردوں گا",
    "کچھ نہیں کروں گا",
    "مدد کروں گا",
    "معلوم نہیں",
    "1"
  ],
  "ہمارے مذہب میں اظہار رائے کی آزادی نہیں ہے۔": [
    "متفق",
    "نا متفق",
    "بلکل متفق",
    "کچھ کہہ نہیں سکتے",
    "1"
  ],
  "کیا مختلف ہیں؟": [
    "معلم",
    "پروفیسر",
    "پرنسپل",
    "طالب علم",
    "3"
  ],
  "اگر ایک گاڑی ایک گھنٹے میں 90 کلومیٹر کی رفتار سے فاصلہ طے کرتی ہے تو 6 منٹ میں کتنا فاصلہ طے کرے گی؟": [
    "9km",
    "60km",
    "12km",
    "ان میں سے کوئی بھی نہیں",
    "0"
  ],
  "اگر آپکا ماتحت کام مکمل نہ کر سکے تو کیا کریں گے؟": [
    "اضافی وقت میں کام مکمل کریں گے",
    "سزا دیں گے",
    "سمجھایں گے",
    "کچھ کہہ نہیں سکتے",
    "0"
  ],
  "انسان کو دوسروں کی اصلاح کے ساتھ اپنی اصلاح کی زیادہ ضرورت ہے۔": [
    "متفق",
    "نا متفق",
    "بلکل متفق",
    "کچھ کہہ نہیں سکتے",
    "0"
  ],
  "اگر ایک بس میں 32 مسافر سفر کر سکتے ہیں تو 192 مسافر کتنی بسوں میں سفر کریں گے۔": [
    "6",
    "7",
    "10",
    "12",
    "0"
  ],
  "۔1+2+3+4+5+6+7+8+9+1 کا مجموعہ کیا ہے؟": [
    "50",
    "55",
    "65",
    "ان میں سے کوئی بھی نہیں",
    "1"
  ],
  "عورت کو علاج کیلئے صرف لیڈی ڈاکٹر کے پاس جانا چاہیے۔": [
    "متفق",
    "نا متفق",
    "بلکل متفق",
    "کچھ کہہ نہیں سکتے",
    "1"
  ],
  "1,5,9,.... Complete the series.": [
    "12",
    "13",
    "19",
    "ان میں سے کوئی بھی نہیں",
    "1"
  ],
  "کیا دینی مدارس شرپسندی پھیلانے کی اصل وجہ ہیں؟": [
    "متفق",
    "بلکل نا متفق",
    "بلکل متفق",
    "نا متفق",
    "1"
  ],
  "چیتا، ہرن، شیر، بلی میں سے کونسی چیز مختلف ہے؟": [
    "چیتا",
    "شیر",
    "ہرن",
    "بلی",
    "2"
  ],
  "گائے، بکری، بطخ، بھیڑ میں سے کونسی چیز مختلف ہے؟": [
    "بطخ",
    "گائے",
    "بکری",
    "بھیڑ",
    "0"
  ],
  "جہاز کو اڑانے کیلئے کونسی چیز مدد دیتی ہے؟": [
    "انجن",
    "پر(فین)۔",
    "پائیلٹ",
    "ائیرہوسٹس",
    "1"
  ],
  "اگر 3 کتابوں کی قیمت 21 روپے ہے تو 9 کتابوں کی قیمت کتنی ہوگی؟": [
    "Rs 630",
    "Rs 27",
    "Rs 60",
    "Rs 63",
    "3"
  ],
  "اگر ایک انڈے کی قیمت 9 روپے ہے تو 21 انڈوں کی قیمت کتنی ہوگی؟": [
    "Rs 18",
    "Rs 189",
    "Rs 190",
    "Rs 198",
    "1"
  ],
  "کیا فرقے کا پرچار کرنا چاہیے؟": [
    "بلکل متفق",
    "متفق",
    "بلکل نا متفق",
    "نا متفق",
    "3"
  ],
  "کیا طلاق لینا عورت کا شرعی حق ہے؟": [
    "بلکل متفق",
    "متفق",
    "بلکل نا متفق",
    "نا متفق",
    "3"
  ],
  "اگر 3 پنسلوں کی قیمت 9 روپے ہے تو 5 پنسلوں کی قیمت کیا ہوگی؟": [
    "Rs 5",
    "Rs 15",
    "Rs 150",
    "Rs 10",
    "2"
  ],
  "۔20 کا 25 فیصد کتنا ہے؟": [
    "2",
    "4",
    "6",
    "5",
    "3"
  ],
  "اگر ایک گاڑی 3 کلومیٹر فی گھنٹہ کی رفتار سے چلتی ہے تو 2 کلومیٹر کا فاصلہ کتنے وقت میں طے کرے گی؟": [
    "45 منٹ",
    "40 منٹ",
    "30 منٹ",
    "20 منٹ",
    "1"
  ],
  "اگر 3 بسکٹ والے پیکٹ کی قیمت 21 روپے ہے تو 9 بسکٹ کی قیمت کتنی ہوگی؟": [
    "Rs 60",
    "Rs 36",
    "Rs 63",
    "Rs 630",
    "2"
  ]
}